
{
    "a3124670-16eb-451d-ab89-e7dcb7979816": [
        {
            "action": "Save",
            "dateTime": "2019-11-23T23:06:39.364",
            "value": 9794,
            "when": "23 Nov 2019 at 23:11"
        },
        {
            "action": "Save",
            "dateTime": "2020-03-06T13:30:43.913",
            "value": 7308,
            "when": "06 Mar 2020 at 13:03"
        }
    ],
    "6a3d949c-d4a5-4ad4-aac4-2847c0140a85": [
        {
            "action": "Drive",
            "dateTime": "2019-05-13T22:55:45.358",
            "value": 2090,
            "when": "13 May 2019 at 22:05"
        },
        {
            "action": "Drive",
            "dateTime": "2019-08-01T23:56:49.714",
            "value": 9379,
            "when": "01 Aug 2019 at 23:08"
        }
    ],
    "6cc43771-2b11-4b59-9aca-bcfa4d73e8f8": [
        {
            "action": "Drive",
            "dateTime": "2019-11-02T06:36:49.477",
            "value": 5059,
            "when": "02 Nov 2019 at 06:11"
        },
        {
            "action": "Drive",
            "dateTime": "2019-09-08T15:40:26.317",
            "value": 8870,
            "when": "08 Sep 2019 at 15:09"
        }
    ],
    "d13ba7c4-6c7d-4661-ad6d-858a1731e8fd": [
        {
            "action": "Drive",
            "dateTime": "2019-10-25T16:32:30.575",
            "value": 2940,
            "when": "25 Oct 2019 at 16:10"
        },
        {
            "action": "Drive",
            "dateTime": "2020-04-04T08:46:43.552",
            "value": 5669,
            "when": "04 Apr 2020 at 08:04"
        }
    ],
    "fbabdbec-8717-427c-b768-39eb0ef464d1": [
        {
            "action": "Save",
            "dateTime": "2019-12-27T19:50:35.924",
            "value": 1078,
            "when": "27 Dec 2019 at 19:12"
        },
        {
            "action": "Save",
            "dateTime": "2019-05-05T22:04:21.466",
            "value": 7639,
            "when": "05 May 2019 at 22:05"
        }
    ],
    "9c12ba10-d231-4715-bda3-1f219caf46c0": [
        {
            "action": "Steps",
            "dateTime": "2019-05-03T07:10:08.965",
            "value": 375,
            "when": "03 May 2019 at 07:05"
        },
        {
            "action": "Steps",
            "dateTime": "2020-02-17T20:21:42.908",
            "value": 754,
            "when": "17 Feb 2020 at 20:02"
        }
    ],
    "bde2d353-c513-4e60-9fe5-39a9636d282f": [
        {
            "action": "Save",
            "dateTime": "2019-11-07T09:50:54.067",
            "value": 2685,
            "when": "07 Nov 2019 at 09:11"
        },
        {
            "action": "Save",
            "dateTime": "2020-04-13T13:22:22.145",
            "value": 5760,
            "when": "13 Apr 2020 at 13:04"
        }
    ],
    "83ddc3bb-93c6-40e5-9a10-fc16d4068408": [
        {
            "action": "CheckUp",
            "dateTime": "2019-10-01T11:32:59.903",
            "value": 3054,
            "when": "01 Oct 2019 at 11:10"
        },
        {
            "action": "CheckUp",
            "dateTime": "2019-06-16T03:27:43.199",
            "value": 8508,
            "when": "16 Jun 2019 at 03:06"
        }
    ],
    "089a1dec-a96c-4572-86bb-2a22d5c7bbbb": [
        {
            "action": "Steps",
            "dateTime": "2019-06-06T14:11:02.21",
            "value": 3232,
            "when": "06 Jun 2019 at 14:06"
        },
        {
            "action": "Steps",
            "dateTime": "2020-01-24T03:23:37.346",
            "value": 2393,
            "when": "24 Jan 2020 at 03:01"
        }
    ],
    "2e175db3-fd69-4004-95df-6f99fa91f210": [
        {
            "action": "CheckUp",
            "dateTime": "2019-10-07T15:18:08.019",
            "value": 8603,
            "when": "07 Oct 2019 at 15:10"
        },
        {
            "action": "CheckUp",
            "dateTime": "2019-06-27T19:50:36.899",
            "value": 8197,
            "when": "27 Jun 2019 at 19:06"
        }
    ],
    "64abc30b-21bd-4beb-860d-a5aba69798c8": [
        {
            "action": "CheckUp",
            "dateTime": "2020-04-19T20:12:41.487",
            "value": 8097,
            "when": "19 Apr 2020 at 20:04"
        },
        {
            "action": "CheckUp",
            "dateTime": "2019-10-02T01:11:17.102",
            "value": 6472,
            "when": "02 Oct 2019 at 01:10"
        }
    ],
    "c90bcccd-f900-4c5b-84eb-f5d30bb28298": [
        {
            "action": "Steps",
            "dateTime": "2019-09-26T08:33:19.534",
            "value": 5598,
            "when": "26 Sep 2019 at 08:09"
        },
        {
            "action": "Steps",
            "dateTime": "2019-09-21T10:43:10.672",
            "value": 2681,
            "when": "21 Sep 2019 at 10:09"
        }
    ],
    "d5f3f78c-9104-48c7-9aa9-52a3eef0a896": [
        {
            "action": "CheckUp",
            "dateTime": "2019-10-17T08:07:23.256",
            "value": 8123,
            "when": "17 Oct 2019 at 08:10"
        },
        {
            "action": "CheckUp",
            "dateTime": "2020-04-01T04:08:16.496",
            "value": 3285,
            "when": "01 Apr 2020 at 04:04"
        }
    ],
    "07b1ddf0-af06-41e5-858d-0c188fed230b": [
        {
            "action": "Drive",
            "dateTime": "2019-08-17T14:27:07.857",
            "value": 6644,
            "when": "17 Aug 2019 at 14:08"
        },
        {
            "action": "Drive",
            "dateTime": "2019-12-27T08:17:38.592",
            "value": 4227,
            "when": "27 Dec 2019 at 08:12"
        }
    ],
    "3a4009e6-5513-4fe5-b391-9c8d34a67079": [
        {
            "action": "Save",
            "dateTime": "2019-12-09T01:06:48.248",
            "value": 1403,
            "when": "09 Dec 2019 at 01:12"
        },
        {
            "action": "Save",
            "dateTime": "2020-02-18T06:40:28.667",
            "value": 3914,
            "when": "18 Feb 2020 at 06:02"
        }
    ],
    "da594a0b-cfd8-42dc-8997-d94041d8824a": [
        {
            "action": "Drive",
            "dateTime": "2019-07-19T13:41:27.29",
            "value": 4848,
            "when": "19 Jul 2019 at 13:07"
        },
        {
            "action": "Drive",
            "dateTime": "2019-11-02T22:36:27.188",
            "value": 8064,
            "when": "02 Nov 2019 at 22:11"
        }
    ],
    "56405c21-04a4-4c22-b2bb-7e6466019ded": [
        {
            "action": "CheckUp",
            "dateTime": "2019-12-29T23:49:44.643",
            "value": 3456,
            "when": "29 Dec 2019 at 23:12"
        },
        {
            "action": "CheckUp",
            "dateTime": "2020-04-21T17:39:33.514",
            "value": 7231,
            "when": "21 Apr 2020 at 17:04"
        }
    ],
    "90443d40-abbe-4040-83dc-5e08ec452e3f": [
        {
            "action": "CheckUp",
            "dateTime": "2019-08-01T07:15:49.13",
            "value": 7577,
            "when": "01 Aug 2019 at 07:08"
        },
        {
            "action": "CheckUp",
            "dateTime": "2019-06-23T22:21:56.811",
            "value": 304,
            "when": "23 Jun 2019 at 22:06"
        }
    ],
    "c9a24e83-1c49-4a46-b12d-20f8a4788a16": [
        {
            "action": "Save",
            "dateTime": "2019-06-17T19:29:10.182",
            "value": 5640,
            "when": "17 Jun 2019 at 19:06"
        },
        {
            "action": "Save",
            "dateTime": "2020-01-18T08:01:27.4",
            "value": 2892,
            "when": "18 Jan 2020 at 08:01"
        }
    ],
    "51ac6824-e05c-492a-bd25-145bc67d9122": [
        {
            "action": "Steps",
            "dateTime": "2020-04-03T04:58:52.85",
            "value": 3917,
            "when": "03 Apr 2020 at 04:04"
        },
        {
            "action": "Steps",
            "dateTime": "2020-03-18T02:59:17.279",
            "value": 7102,
            "when": "18 Mar 2020 at 02:03"
        }
    ],
    "10a85beb-8063-4efa-9b45-74aaf5dbbf4a": [
        {
            "action": "Drive",
            "dateTime": "2019-12-12T19:18:09.299",
            "value": 7890,
            "when": "12 Dec 2019 at 19:12"
        },
        {
            "action": "Drive",
            "dateTime": "2019-09-06T17:48:51.054",
            "value": 6771,
            "when": "06 Sep 2019 at 17:09"
        }
    ],
    "acf3bf4f-cc22-4a12-b0b7-1eabd275af83": [
        {
            "action": "Steps",
            "dateTime": "2020-01-02T08:47:01.77",
            "value": 9674,
            "when": "02 Jan 2020 at 08:01"
        },
        {
            "action": "Steps",
            "dateTime": "2019-12-05T16:42:57.895",
            "value": 6719,
            "when": "05 Dec 2019 at 16:12"
        }
    ],
    "f136f83c-f07a-4190-9c17-4ad38972c27e": [
        {
            "action": "Drive",
            "dateTime": "2019-09-12T02:08:23.525",
            "value": 9598,
            "when": "12 Sep 2019 at 02:09"
        },
        {
            "action": "Drive",
            "dateTime": "2019-10-21T21:11:10.643",
            "value": 1028,
            "when": "21 Oct 2019 at 21:10"
        }
    ],
    "fb36ff5b-6727-46d2-a730-7b815353f690": [
        {
            "action": "Steps",
            "dateTime": "2019-08-29T08:28:12.333",
            "value": 6205,
            "when": "29 Aug 2019 at 08:08"
        },
        {
            "action": "Steps",
            "dateTime": "2019-08-30T23:50:53.63",
            "value": 4701,
            "when": "30 Aug 2019 at 23:08"
        }
    ],
    "9ca4847c-2e77-43a1-9478-fa37d6b950d3": [
        {
            "action": "Save",
            "dateTime": "2019-09-19T18:35:21.116",
            "value": 654,
            "when": "19 Sep 2019 at 18:09"
        },
        {
            "action": "Save",
            "dateTime": "2020-01-02T14:55:15.065",
            "value": 2259,
            "when": "02 Jan 2020 at 14:01"
        }
    ],
    "63d116aa-3091-4e0a-b492-57dd6918df9c": [
        {
            "action": "Steps",
            "dateTime": "2019-06-30T05:35:20.586",
            "value": 6152,
            "when": "30 Jun 2019 at 05:06"
        },
        {
            "action": "Steps",
            "dateTime": "2020-03-17T22:17:37.851",
            "value": 5481,
            "when": "17 Mar 2020 at 22:03"
        }
    ],
    "a125ca4f-5616-4ed4-92f8-2ae7ca646e38": [
        {
            "action": "Save",
            "dateTime": "2019-11-28T10:09:33.249",
            "value": 7670,
            "when": "28 Nov 2019 at 10:11"
        },
        {
            "action": "Save",
            "dateTime": "2019-12-06T08:17:33.202",
            "value": 6771,
            "when": "06 Dec 2019 at 08:12"
        }
    ],
    "6aa6dcc1-d0cd-45a7-8b5c-d3c6cf1e5fa6": [
        {
            "action": "Drive",
            "dateTime": "2019-10-15T13:41:07.222",
            "value": 3547,
            "when": "15 Oct 2019 at 13:10"
        },
        {
            "action": "Drive",
            "dateTime": "2019-12-07T06:13:52.43",
            "value": 7653,
            "when": "07 Dec 2019 at 06:12"
        }
    ],
    "271c7683-abbf-4e14-a857-e7c3c8ff4ab0": [
        {
            "action": "CheckUp",
            "dateTime": "2019-12-22T17:00:29.119",
            "value": 5201,
            "when": "22 Dec 2019 at 17:12"
        },
        {
            "action": "CheckUp",
            "dateTime": "2020-02-12T20:34:26.196",
            "value": 8387,
            "when": "12 Feb 2020 at 20:02"
        }
    ],
    "db1683e7-c358-4e4a-b200-42a9296160d8": [
        {
            "action": "Save",
            "dateTime": "2020-02-03T00:51:07.676",
            "value": 8872,
            "when": "03 Feb 2020 at 00:02"
        },
        {
            "action": "Save",
            "dateTime": "2019-06-05T19:33:29.176",
            "value": 8840,
            "when": "05 Jun 2019 at 19:06"
        }
    ],
    "d2552177-1445-4f02-91a2-8865bb050610": [
        {
            "action": "Steps",
            "dateTime": "2020-03-10T20:37:20.944",
            "value": 444,
            "when": "10 Mar 2020 at 20:03"
        },
        {
            "action": "Steps",
            "dateTime": "2019-08-21T09:47:36.815",
            "value": 759,
            "when": "21 Aug 2019 at 09:08"
        }
    ],
    "c61df030-f193-4dbb-8c67-ca1980ad3521": [
        {
            "action": "Steps",
            "dateTime": "2020-04-17T04:01:45.333",
            "value": 2977,
            "when": "17 Apr 2020 at 04:04"
        },
        {
            "action": "Steps",
            "dateTime": "2019-08-10T05:17:08.442",
            "value": 1840,
            "when": "10 Aug 2019 at 05:08"
        }
    ],
    "2707ef06-d394-41e9-baca-9fbc899d3f20": [
        {
            "action": "Steps",
            "dateTime": "2020-04-29T23:50:22.667",
            "value": 2614,
            "when": "29 Apr 2020 at 23:04"
        },
        {
            "action": "Steps",
            "dateTime": "2019-08-03T04:06:05.815",
            "value": 638,
            "when": "03 Aug 2019 at 04:08"
        }
    ],
    "8472e4a2-c26a-4041-be37-e2c2af167862": [
        {
            "action": "Save",
            "dateTime": "2019-08-03T08:18:33.335",
            "value": 6090,
            "when": "03 Aug 2019 at 08:08"
        },
        {
            "action": "Save",
            "dateTime": "2020-04-16T03:35:51.23",
            "value": 4925,
            "when": "16 Apr 2020 at 03:04"
        }
    ],
    "c586d351-cea5-49d4-8842-365728d7a218": [
        {
            "action": "Save",
            "dateTime": "2019-06-24T05:43:16.046",
            "value": 2784,
            "when": "24 Jun 2019 at 05:06"
        },
        {
            "action": "Save",
            "dateTime": "2019-12-25T18:01:45.913",
            "value": 1167,
            "when": "25 Dec 2019 at 18:12"
        }
    ],
    "ac5e2b50-e710-4471-8400-54f8412ab4c1": [
        {
            "action": "CheckUp",
            "dateTime": "2019-08-29T12:16:09.026",
            "value": 4727,
            "when": "29 Aug 2019 at 12:08"
        },
        {
            "action": "CheckUp",
            "dateTime": "2019-05-20T06:29:49.582",
            "value": 5942,
            "when": "20 May 2019 at 06:05"
        }
    ],
    "019a3c99-d7c6-458e-9dc8-aacc4cb40f06": [
        {
            "action": "CheckUp",
            "dateTime": "2019-09-10T06:54:27.002",
            "value": 5977,
            "when": "10 Sep 2019 at 06:09"
        },
        {
            "action": "CheckUp",
            "dateTime": "2019-05-05T04:28:27.352",
            "value": 2190,
            "when": "05 May 2019 at 04:05"
        }
    ],
    "4f931428-8197-4738-b639-6a31e3278486": [
        {
            "action": "Drive",
            "dateTime": "2019-12-30T07:39:49.086",
            "value": 444,
            "when": "30 Dec 2019 at 07:12"
        },
        {
            "action": "Drive",
            "dateTime": "2019-07-10T05:21:31.644",
            "value": 9934,
            "when": "10 Jul 2019 at 05:07"
        }
    ],
    "81fbd922-094c-4e9f-8362-cbfcceb4b9df": [
        {
            "action": "Drive",
            "dateTime": "2020-03-03T19:04:42.105",
            "value": 5744,
            "when": "03 Mar 2020 at 19:03"
        },
        {
            "action": "Drive",
            "dateTime": "2019-06-25T07:33:45.074",
            "value": 1853,
            "when": "25 Jun 2019 at 07:06"
        }
    ],
    "c75beb58-f7a5-4d36-bba8-d343339879dc": [
        {
            "action": "CheckUp",
            "dateTime": "2019-05-04T11:40:52.275",
            "value": 4898,
            "when": "04 May 2019 at 11:05"
        },
        {
            "action": "CheckUp",
            "dateTime": "2020-03-24T06:58:57.052",
            "value": 5963,
            "when": "24 Mar 2020 at 06:03"
        }
    ]
}